py_sarvcrm_api-1.4.1.dist-info/licenses/LICENSE
sarvcrm_api/__init__.py
sarvcrm_api/__version__.py
sarvcrm_api/_client.py
sarvcrm_api/_exceptions.py
sarvcrm_api/_mixins.py
sarvcrm_api/_type_hints.py
sarvcrm_api/_url.py
sarvcrm_api/modules/__init__.py
sarvcrm_api/modules/_base.py
sarvcrm_api/modules/_mixins.py
sarvcrm_api/modules/accounts.py
sarvcrm_api/modules/acl_roles.py
sarvcrm_api/modules/aos_contracts.py
sarvcrm_api/modules/aos_invoices.py
sarvcrm_api/modules/aos_pdf_templates.py
sarvcrm_api/modules/aos_product_categories.py
sarvcrm_api/modules/aos_products.py
sarvcrm_api/modules/aos_quotes.py
sarvcrm_api/modules/approval.py
sarvcrm_api/modules/asol_project.py
sarvcrm_api/modules/branches.py
sarvcrm_api/modules/bugs.py
sarvcrm_api/modules/calls.py
sarvcrm_api/modules/campaigns.py
sarvcrm_api/modules/cases.py
sarvcrm_api/modules/communications.py
sarvcrm_api/modules/communications_target.py
sarvcrm_api/modules/communications_template.py
sarvcrm_api/modules/contacts.py
sarvcrm_api/modules/deposits.py
sarvcrm_api/modules/documents.py
sarvcrm_api/modules/emails.py
sarvcrm_api/modules/knowledge_base.py
sarvcrm_api/modules/knowledge_base_categories.py
sarvcrm_api/modules/leads.py
sarvcrm_api/modules/meetings.py
sarvcrm_api/modules/notes.py
sarvcrm_api/modules/notifications.py
sarvcrm_api/modules/obj_conditions.py
sarvcrm_api/modules/obj_indicators.py
sarvcrm_api/modules/obj_objectives.py
sarvcrm_api/modules/opportunities.py
sarvcrm_api/modules/payments.py
sarvcrm_api/modules/purchase_order.py
sarvcrm_api/modules/sc_competitor.py
sarvcrm_api/modules/sc_contract.py
sarvcrm_api/modules/sc_contract_management.py
sarvcrm_api/modules/service_centers.py
sarvcrm_api/modules/tasks.py
sarvcrm_api/modules/timesheet.py
sarvcrm_api/modules/users.py
sarvcrm_api/modules/vendors.py
py_sarvcrm_api-1.4.1.dist-info/METADATA
py_sarvcrm_api-1.4.1.dist-info/WHEEL
py_sarvcrm_api-1.4.1.dist-info/top_level.txt
py_sarvcrm_api-1.4.1.dist-info/RECORD
