Metadata-Version: 2.4
Name: py-sarvcrm-api
Version: 1.4.1
Summary: Simple sarvcrm api module
Home-page: https://github.com/Radin-System/py-sarvcrm-api
Author: hmohammad
Author-email: hmohammad <hmohammad2520@gmail.com>
License: MIT License
Project-URL: Homepage, https://github.com/hmohammad2520-org/py-sarvcrm-api
Project-URL: BugTracker, https://github.com/hmohammad2520-org/py-sarvcrm-api/issues
Keywords: python,library,sarvcrm,hamkaransystem,api
Classifier: Programming Language :: Python :: 3
Classifier: License :: OSI Approved :: MIT License
Classifier: Operating System :: OS Independent
Requires-Python: >=3.9
License-File: LICENSE
Requires-Dist: requests==2.32.4
Requires-Dist: requests_cache==1.2.1
Requires-Dist: classmods==1.2.1
Dynamic: author
Dynamic: home-page
Dynamic: license-file
